hipar/__init__.py
hipar/check.py
hipar/data.py
hipar/discretize.py
hipar/hipar.py
hipar/metrics.py
hipar/output.py
hipar/patterns.py
hipar/rule_selection.py
hipar/types.py
hipar/utils.py
hipar/resources/datasets/cpu.data
hipar-0.1.0.dist-info/LICENSE
hipar-0.1.0.dist-info/METADATA
hipar-0.1.0.dist-info/WHEEL
hipar-0.1.0.dist-info/top_level.txt
hipar-0.1.0.dist-info/RECORD
