Metadata-Version: 2.1
Name: hipar
Version: 0.1.0
Summary: Hierarchical Pattern-aided Regression
Home-page: https://gitlab.inria.fr/lgalarra/hipar
Maintainer: Luis Galárraga
Maintainer-email: luis.galarraga@inria.fr
License: BSD 3-Clause
Download-URL: https://gitlab.inria.fr/lgalarra/hipar
Keywords: regression,pattern mining
Platform: UNKNOWN
Classifier: Development Status :: 3 - Alpha
Classifier: Intended Audience :: Science/Research
Classifier: Intended Audience :: Developers
Classifier: License :: OSI Approved
Classifier: Programming Language :: Python
Classifier: Topic :: Software Development
Classifier: Topic :: Scientific/Engineering
Classifier: Operating System :: Microsoft :: Windows
Classifier: Operating System :: POSIX
Classifier: Operating System :: Unix
Classifier: Operating System :: MacOS
Classifier: Programming Language :: Python :: 3.8
Classifier: Programming Language :: Python :: 3 :: Only
Requires-Python: >=3.8, <4
Requires-Dist: pandas (>=1.1.5)
Requires-Dist: numpy (>=1.19)
Requires-Dist: scipy (>=1.5.4)
Requires-Dist: scikit-learn (>=0.23)
Requires-Dist: mdlp-discretization (>=0.3.3)
Requires-Dist: ortools (>=8.1)
Requires-Dist: sortedcontainers (>=2.3.0)
Provides-Extra: docs
Requires-Dist: sphinx ; extra == 'docs'
Requires-Dist: sphinx-gallery ; extra == 'docs'
Requires-Dist: sphinx-rtd-theme ; extra == 'docs'
Requires-Dist: numpydoc ; extra == 'docs'
Requires-Dist: matplotlib ; extra == 'docs'
Provides-Extra: tests
Requires-Dist: pytest ; extra == 'tests'
